regtabletotext/__init__.py
regtabletotext/funs.py
tests/__init__.py
regtabletotext-0.0.10.dist-info/LICENSE
regtabletotext-0.0.10.dist-info/METADATA
regtabletotext-0.0.10.dist-info/WHEEL
regtabletotext-0.0.10.dist-info/top_level.txt
regtabletotext-0.0.10.dist-info/RECORD
