Metadata-Version: 2.1
Name: regtabletotext
Version: 0.0.10
Summary: Helpers to print regression output as well-formated text
Home-page: https://github.com/christophscheuch/regtabletotext
Download-URL: https://pypi.org/project/regtabletotext/
Author: Christoph Scheuch
Author-email: christoph.scheuch@gmail.com
License: MIT
Keywords: Regression,Table,Formatting,Quarto,Text
License-File: LICENSE
Requires-Dist: pandas
Requires-Dist: tabulate
